cp_tcgen-0.11.1.data/scripts/genout
cp_tcgen-0.11.1.data/scripts/tcgen
tcgen/__init__.py
tcgen/_version.py
tcgen/datatypes.py
tcgen/generator.py
tcgen/primitives.py
tcgen/utils/__init__.py
tcgen/utils/constants.py
tcgen/utils/random.py
cp_tcgen-0.11.1.dist-info/LICENSE
cp_tcgen-0.11.1.dist-info/METADATA
cp_tcgen-0.11.1.dist-info/WHEEL
cp_tcgen-0.11.1.dist-info/top_level.txt
cp_tcgen-0.11.1.dist-info/RECORD
