Metadata-Version: 2.1
Name: cp-tcgen
Version: 0.11.1
Summary: Test case generator. Quickly design and generate test cases without all the bulk
Home-page: https://github.com/JoshuaTianYangLiu/tcgen
Author: Joshua Liu
Author-email: joshualiu@youarefantastic.com
License: MIT
Keywords: program competitive programming codeforces
Platform: UNKNOWN
License-File: LICENSE
Requires-Dist: pytest
Requires-Dist: flake8
Requires-Dist: sympy
